blackoryx/__init__.py
blackoryx/engine.py
blackoryx/main.py
blackoryx/parser.py
blackoryx-0.1.0.dist-info/METADATA
blackoryx-0.1.0.dist-info/WHEEL
blackoryx-0.1.0.dist-info/entry_points.txt
blackoryx-0.1.0.dist-info/top_level.txt
blackoryx-0.1.0.dist-info/RECORD
