Metadata-Version: 2.4
Name: blackoryx
Version: 0.1.0
Summary: A script-based animation engine powered by ORYX language.
Author: Atharv Puri
Author-email: Atharv <vincorus.edu@gmail.com>
License: MIT
Requires-Python: >=3.11
Requires-Dist: moviepy==1.0.3
Requires-Dist: imageio==2.31.1
Requires-Dist: imageio-ffmpeg==0.4.8
Requires-Dist: numpy
Requires-Dist: pillow
Requires-Dist: tqdm
Requires-Dist: decorator==4.4.2
Requires-Dist: proglog
Dynamic: author
Dynamic: requires-python
